README.rst
setup.cfg
setup.py
ideam/__init__.py
ideam/entity.py
ideam.egg-info/PKG-INFO
ideam.egg-info/SOURCES.txt
ideam.egg-info/dependency_links.txt
ideam.egg-info/requires.txt
ideam.egg-info/top_level.txt