Metadata-Version: 1.2
Name: ideam
Version: 0.0.3
Summary: Python SDK for IoT Data Exchange & Analytics Middleware
Home-page: https://github.com/rbccps-iisc/ideam-python-sdk
Author: Harish Anand
Author-email: smartcity@rbccps.org
License: ISC
Download-URL: https://github.com/rbccps-iisc/ideam-python-sdk/archive/0.0.3.tar.gz
Keywords: IoT,smartcity,ideam
Platform: UNKNOWN
Classifier: Development Status :: 5 - Production/Stable
Classifier: Topic :: Internet
Classifier: Topic :: Scientific/Engineering :: Information Analysis
Classifier: Topic :: Software Development :: Libraries :: Python Modules
Classifier: Intended Audience :: Developers
Classifier: License :: OSI Approved :: ISC License (ISCL)
Classifier: Operating System :: POSIX :: Linux
Classifier: Operating System :: MacOS
Classifier: Programming Language :: Python :: 3 :: Only
Classifier: Programming Language :: Python :: 3.5
Classifier: Programming Language :: Python :: 3.6
Requires-Python: >=3.5.4
